dask_avro/__init__.py
dask_avro/compat.py
dask_avro-0.3.0.dist-info/METADATA
dask_avro-0.3.0.dist-info/RECORD
dask_avro-0.3.0.dist-info/WHEEL
dask_avro-0.3.0.dist-info/top_level.txt
