Metadata-Version: 2.1
Name: dask-avro
Version: 0.3.0
Summary: Avro reader for Dask.
Home-page: https://github.com/rmax/dask-avro
Author: Rolando (Max) Espinoza
Author-email: rolando@rmax.io
License: MIT
Keywords: dask-avro
Platform: UNKNOWN
Classifier: Development Status :: 2 - Pre-Alpha
Classifier: Intended Audience :: Developers
Classifier: License :: OSI Approved :: MIT License
Classifier: Natural Language :: English
Classifier: Programming Language :: Python :: 2
Classifier: Programming Language :: Python :: 2.7
Classifier: Programming Language :: Python :: 3
Classifier: Programming Language :: Python :: 3.5
Classifier: Programming Language :: Python :: 3.6
Requires-Dist: dask[bag]
Requires-Dist: fastavro (>=0.17.0)
